st_comments/__init__.py
st_comments/frontend/build/asset-manifest.json
st_comments/frontend/build/bootstrap.min.css
st_comments/frontend/build/index.html
st_comments/frontend/build/precache-manifest.2178a74dccf6e88c305e1192b2791dd9.js
st_comments/frontend/build/precache-manifest.2a5cfe9e186bf6bc904d415d1854075d.js
st_comments/frontend/build/precache-manifest.32be651d125a7b7a83fc3c4ab9a89dd2.js
st_comments/frontend/build/precache-manifest.3ceea577b966f867b77e9944aed620d9.js
st_comments/frontend/build/precache-manifest.43d478129138b9bca9e151c1c5dea5e0.js
st_comments/frontend/build/precache-manifest.4a0dfa5b935788613d1e5dc19b39f704.js
st_comments/frontend/build/precache-manifest.4c6629fbc11735316121ccba7eb9379d.js
st_comments/frontend/build/precache-manifest.6a9e45a65cd35c694554c74844ac3787.js
st_comments/frontend/build/precache-manifest.7d43e8077c06d7adadc854d93d7071ba.js
st_comments/frontend/build/precache-manifest.8f1c93e7d236cddd7ed6dade4d904bd3.js
st_comments/frontend/build/precache-manifest.93d267df5529edee488ed93e9c7dbf67.js
st_comments/frontend/build/precache-manifest.a429dd3454f6e9f0aeb52db709cd98bc.js
st_comments/frontend/build/precache-manifest.a62791e8b9afed62e93f2b0c1c439b97.js
st_comments/frontend/build/precache-manifest.e5b1ff34bb3ed32eef2351455ed24ab0.js
st_comments/frontend/build/service-worker.js
st_comments/frontend/build/static/css/2.70233154.chunk.css
st_comments/frontend/build/static/css/2.70233154.chunk.css.map
st_comments/frontend/build/static/js/2.17403f52.chunk.js
st_comments/frontend/build/static/js/2.17403f52.chunk.js.LICENSE.txt
st_comments/frontend/build/static/js/2.17403f52.chunk.js.map
st_comments/frontend/build/static/js/2.38b6c8dd.chunk.js
st_comments/frontend/build/static/js/2.38b6c8dd.chunk.js.LICENSE.txt
st_comments/frontend/build/static/js/2.38b6c8dd.chunk.js.map
st_comments/frontend/build/static/js/2.57035af5.chunk.js
st_comments/frontend/build/static/js/2.57035af5.chunk.js.LICENSE.txt
st_comments-0.0.14.dist-info/LICENSE
st_comments-0.0.14.dist-info/METADATA
st_comments-0.0.14.dist-info/WHEEL
st_comments-0.0.14.dist-info/top_level.txt
st_comments-0.0.14.dist-info/RECORD
