Metadata-Version: 2.1
Name: st-comments
Version: 0.0.14
Summary: Streamlit Component for Comments
Author: 
Author-email: 
Requires-Python: >=3.6
License-File: LICENSE
Requires-Dist: streamlit (>=0.63)
